eland/__init__.py
eland/_version.py
eland/actions.py
eland/arithmetics.py
eland/common.py
eland/conftest.py
eland/dataframe.py
eland/etl.py
eland/field_mappings.py
eland/filter.py
eland/groupby.py
eland/index.py
eland/ndframe.py
eland/operations.py
eland/py.typed
eland/query.py
eland/query_compiler.py
eland/series.py
eland/tasks.py
eland/utils.py
eland/cli/__init__.py
eland/cli/eland_import_hub_model.py
eland/ml/__init__.py
eland/ml/_model_serializer.py
eland/ml/_optional.py
eland/ml/common.py
eland/ml/ml_model.py
eland/ml/ltr/__init__.py
eland/ml/ltr/feature_logger.py
eland/ml/ltr/ltr_model_config.py
eland/ml/pytorch/__init__.py
eland/ml/pytorch/_pytorch_model.py
eland/ml/pytorch/nlp_ml_model.py
eland/ml/pytorch/traceable_model.py
eland/ml/pytorch/transformers.py
eland/ml/pytorch/wrappers.py
eland/ml/transformers/__init__.py
eland/ml/transformers/base.py
eland/ml/transformers/lightgbm.py
eland/ml/transformers/sklearn.py
eland/ml/transformers/xgboost.py
eland/plotting/__init__.py
eland/plotting/_core.py
eland/plotting/_matplotlib/__init__.py
eland/plotting/_matplotlib/hist.py
eland-9.0.1.dist-info/licenses/LICENSE.txt
eland-9.0.1.dist-info/licenses/NOTICE.txt
eland-9.0.1.dist-info/METADATA
eland-9.0.1.dist-info/WHEEL
eland-9.0.1.dist-info/entry_points.txt
eland-9.0.1.dist-info/top_level.txt
eland-9.0.1.dist-info/RECORD
