Metadata-Version: 2.4
Name: eland
Version: 9.0.1
Summary: Python Client and Toolkit for DataFrames, Big Data, Machine Learning and ETL in Elasticsearch
Home-page: https://github.com/elastic/eland
Author: Steve Dodson
Author-email: steve.dodson@elastic.co
Maintainer: Elastic Client Library Maintainers
Maintainer-email: client-libs@elastic.co
License: Apache-2.0
Keywords: elastic eland pandas python
Classifier: Development Status :: 5 - Production/Stable
Classifier: License :: OSI Approved :: Apache Software License
Classifier: Environment :: Console
Classifier: Operating System :: OS Independent
Classifier: Intended Audience :: Developers
Classifier: Intended Audience :: Science/Research
Classifier: Operating System :: OS Independent
Classifier: Programming Language :: Python
Classifier: Programming Language :: Python :: 3
Classifier: Programming Language :: Python :: 3 :: Only
Classifier: Programming Language :: Python :: 3.9
Classifier: Programming Language :: Python :: 3.10
Classifier: Programming Language :: Python :: 3.11
Classifier: Programming Language :: Python :: 3.12
Classifier: Topic :: Scientific/Engineering
Requires-Python: >=3.9,<3.13
License-File: LICENSE.txt
License-File: NOTICE.txt
Requires-Dist: elasticsearch<10,>=9
Requires-Dist: pandas<3,>=1.5
Requires-Dist: matplotlib>=3.6
Requires-Dist: numpy<2,>=1.2.0
Requires-Dist: packaging
Provides-Extra: xgboost
Requires-Dist: xgboost<2,>=0.90; extra == "xgboost"
Provides-Extra: scikit-learn
Requires-Dist: scikit-learn<1.6,>=1.3; extra == "scikit-learn"
Provides-Extra: lightgbm
Requires-Dist: lightgbm<5,>=3; extra == "lightgbm"
Provides-Extra: pytorch
Requires-Dist: requests<3; extra == "pytorch"
Requires-Dist: torch==2.5.1; extra == "pytorch"
Requires-Dist: tqdm; extra == "pytorch"
Requires-Dist: sentence-transformers<=2.7.0,>=2.1.0; extra == "pytorch"
Requires-Dist: transformers[sentencepiece]>=4.47.0; extra == "pytorch"
Provides-Extra: all
Requires-Dist: xgboost<2,>=0.90; extra == "all"
Requires-Dist: lightgbm<5,>=3; extra == "all"
Requires-Dist: transformers[sentencepiece]>=4.47.0; extra == "all"
Requires-Dist: requests<3; extra == "all"
Requires-Dist: scikit-learn<1.6,>=1.3; extra == "all"
Requires-Dist: tqdm; extra == "all"
Requires-Dist: torch==2.5.1; extra == "all"
Requires-Dist: sentence-transformers<=2.7.0,>=2.1.0; extra == "all"
Dynamic: author
Dynamic: author-email
Dynamic: classifier
Dynamic: description
Dynamic: description-content-type
Dynamic: home-page
Dynamic: keywords
Dynamic: license
Dynamic: license-file
Dynamic: maintainer
Dynamic: maintainer-email
Dynamic: provides-extra
Dynamic: requires-dist
Dynamic: requires-python
Dynamic: summary
